{
  "items": [
    {
      "reportDate": "2025-09-10",
      "activeWorkflows": 35,
      "avgProcessingTime": 4.2,
      "completionRate": 0.967,
      "exceptions": 9,
      "originationWorkflows": 11,
      "creditWorkflows": 17,
      "distributionWorkflows": 11,
      "originationProgress": 71.8,
      "creditProgress": 71.3,
      "distributionProgress": 90.5
    },
    {
      "reportDate": "2025-08-11",
      "activeWorkflows": 32,
      "avgProcessingTime": 4.2,
      "completionRate": 0.93,
      "exceptions": 9,
      "originationWorkflows": 13,
      "creditWorkflows": 15,
      "distributionWorkflows": 8,
      "originationProgress": 80.5,
      "creditProgress": 57.3,
      "distributionProgress": 93.7
    },
    {
      "reportDate": "2025-07-12",
      "activeWorkflows": 37,
      "avgProcessingTime": 2.9,
      "completionRate": 0.935,
      "exceptions": 15,
      "originationWorkflows": 17,
      "creditWorkflows": 11,
      "distributionWorkflows": 9,
      "originationProgress": 84.1,
      "creditProgress": 74.3,
      "distributionProgress": 92.6
    },
    {
      "reportDate": "2025-06-12",
      "activeWorkflows": 35,
      "avgProcessingTime": 4.5,
      "completionRate": 0.954,
      "exceptions": 8,
      "originationWorkflows": 10,
      "creditWorkflows": 14,
      "distributionWorkflows": 10,
      "originationProgress": 68.9,
      "creditProgress": 60.1,
      "distributionProgress": 83.9
    },
    {
      "reportDate": "2025-05-13",
      "activeWorkflows": 37,
      "avgProcessingTime": 2.9,
      "completionRate": 0.931,
      "exceptions": 8,
      "originationWorkflows": 16,
      "creditWorkflows": 14,
      "distributionWorkflows": 12,
      "originationProgress": 65.8,
      "creditProgress": 60.5,
      "distributionProgress": 80.5
    },
    {
      "reportDate": "2025-04-13",
      "activeWorkflows": 25,
      "avgProcessingTime": 4.3,
      "completionRate": 0.954,
      "exceptions": 5,
      "originationWorkflows": 13,
      "creditWorkflows": 10,
      "distributionWorkflows": 8,
      "originationProgress": 77.9,
      "creditProgress": 66.9,
      "distributionProgress": 91.5
    },
    {
      "reportDate": "2025-03-14",
      "activeWorkflows": 38,
      "avgProcessingTime": 3.4,
      "completionRate": 0.965,
      "exceptions": 15,
      "originationWorkflows": 12,
      "creditWorkflows": 9,
      "distributionWorkflows": 12,
      "originationProgress": 76.4,
      "creditProgress": 57.1,
      "distributionProgress": 94.8
    },
    {
      "reportDate": "2025-02-12",
      "activeWorkflows": 41,
      "avgProcessingTime": 4.4,
      "completionRate": 0.947,
      "exceptions": 6,
      "originationWorkflows": 13,
      "creditWorkflows": 11,
      "distributionWorkflows": 5,
      "originationProgress": 80.0,
      "creditProgress": 70.7,
      "distributionProgress": 80.1
    },
    {
      "reportDate": "2025-01-13",
      "activeWorkflows": 41,
      "avgProcessingTime": 3.8,
      "completionRate": 0.966,
      "exceptions": 9,
      "originationWorkflows": 11,
      "creditWorkflows": 12,
      "distributionWorkflows": 9,
      "originationProgress": 80.0,
      "creditProgress": 73.1,
      "distributionProgress": 86.4
    },
    {
      "reportDate": "2024-12-14",
      "activeWorkflows": 35,
      "avgProcessingTime": 3.2,
      "completionRate": 0.979,
      "exceptions": 12,
      "originationWorkflows": 13,
      "creditWorkflows": 9,
      "distributionWorkflows": 5,
      "originationProgress": 82.1,
      "creditProgress": 60.6,
      "distributionProgress": 93.6
    },
    {
      "reportDate": "2024-11-14",
      "activeWorkflows": 30,
      "avgProcessingTime": 3.8,
      "completionRate": 0.938,
      "exceptions": 5,
      "originationWorkflows": 12,
      "creditWorkflows": 14,
      "distributionWorkflows": 12,
      "originationProgress": 69.8,
      "creditProgress": 73.2,
      "distributionProgress": 90.5
    },
    {
      "reportDate": "2024-10-15",
      "activeWorkflows": 38,
      "avgProcessingTime": 4.5,
      "completionRate": 0.934,
      "exceptions": 14,
      "originationWorkflows": 15,
      "creditWorkflows": 11,
      "distributionWorkflows": 5,
      "originationProgress": 82.9,
      "creditProgress": 66.1,
      "distributionProgress": 83.0
    },
    {
      "reportDate": "2024-09-15",
      "activeWorkflows": 43,
      "avgProcessingTime": 3.9,
      "completionRate": 0.964,
      "exceptions": 11,
      "originationWorkflows": 15,
      "creditWorkflows": 14,
      "distributionWorkflows": 10,
      "originationProgress": 74.3,
      "creditProgress": 73.4,
      "distributionProgress": 92.9
    },
    {
      "reportDate": "2024-08-16",
      "activeWorkflows": 28,
      "avgProcessingTime": 3.2,
      "completionRate": 0.935,
      "exceptions": 7,
      "originationWorkflows": 12,
      "creditWorkflows": 17,
      "distributionWorkflows": 10,
      "originationProgress": 68.8,
      "creditProgress": 62.5,
      "distributionProgress": 84.2
    },
    {
      "reportDate": "2024-07-17",
      "activeWorkflows": 28,
      "avgProcessingTime": 4.5,
      "completionRate": 0.954,
      "exceptions": 9,
      "originationWorkflows": 16,
      "creditWorkflows": 9,
      "distributionWorkflows": 12,
      "originationProgress": 82.6,
      "creditProgress": 65.9,
      "distributionProgress": 83.6
    },
    {
      "reportDate": "2024-06-17",
      "activeWorkflows": 36,
      "avgProcessingTime": 3.2,
      "completionRate": 0.952,
      "exceptions": 9,
      "originationWorkflows": 19,
      "creditWorkflows": 16,
      "distributionWorkflows": 6,
      "originationProgress": 80.0,
      "creditProgress": 70.1,
      "distributionProgress": 92.2
    },
    {
      "reportDate": "2024-05-18",
      "activeWorkflows": 32,
      "avgProcessingTime": 3.4,
      "completionRate": 0.945,
      "exceptions": 9,
      "originationWorkflows": 11,
      "creditWorkflows": 13,
      "distributionWorkflows": 10,
      "originationProgress": 72.8,
      "creditProgress": 68.3,
      "distributionProgress": 85.6
    },
    {
      "reportDate": "2024-04-18",
      "activeWorkflows": 39,
      "avgProcessingTime": 3.3,
      "completionRate": 0.93,
      "exceptions": 8,
      "originationWorkflows": 17,
      "creditWorkflows": 15,
      "distributionWorkflows": 8,
      "originationProgress": 75.2,
      "creditProgress": 60.8,
      "distributionProgress": 80.9
    },
    {
      "reportDate": "2024-03-19",
      "activeWorkflows": 40,
      "avgProcessingTime": 4.3,
      "completionRate": 0.94,
      "exceptions": 9,
      "originationWorkflows": 10,
      "creditWorkflows": 14,
      "distributionWorkflows": 12,
      "originationProgress": 82.0,
      "creditProgress": 74.4,
      "distributionProgress": 87.8
    },
    {
      "reportDate": "2024-02-18",
      "activeWorkflows": 41,
      "avgProcessingTime": 3.3,
      "completionRate": 0.979,
      "exceptions": 6,
      "originationWorkflows": 12,
      "creditWorkflows": 18,
      "distributionWorkflows": 10,
      "originationProgress": 79.8,
      "creditProgress": 55.7,
      "distributionProgress": 92.7
    },
    {
      "reportDate": "2024-01-19",
      "activeWorkflows": 43,
      "avgProcessingTime": 2.8,
      "completionRate": 0.98,
      "exceptions": 7,
      "originationWorkflows": 11,
      "creditWorkflows": 15,
      "distributionWorkflows": 5,
      "originationProgress": 71.1,
      "creditProgress": 68.5,
      "distributionProgress": 91.3
    },
    {
      "reportDate": "2023-12-20",
      "activeWorkflows": 32,
      "avgProcessingTime": 3.0,
      "completionRate": 0.932,
      "exceptions": 6,
      "originationWorkflows": 18,
      "creditWorkflows": 16,
      "distributionWorkflows": 10,
      "originationProgress": 81.5,
      "creditProgress": 65.0,
      "distributionProgress": 85.1
    },
    {
      "reportDate": "2023-11-20",
      "activeWorkflows": 42,
      "avgProcessingTime": 3.8,
      "completionRate": 0.947,
      "exceptions": 9,
      "originationWorkflows": 11,
      "creditWorkflows": 12,
      "distributionWorkflows": 9,
      "originationProgress": 78.4,
      "creditProgress": 65.8,
      "distributionProgress": 90.3
    },
    {
      "reportDate": "2023-10-21",
      "activeWorkflows": 42,
      "avgProcessingTime": 3.4,
      "completionRate": 0.962,
      "exceptions": 9,
      "originationWorkflows": 17,
      "creditWorkflows": 10,
      "distributionWorkflows": 11,
      "originationProgress": 68.4,
      "creditProgress": 71.0,
      "distributionProgress": 94.8
    },
    {
      "reportDate": "2023-09-21",
      "activeWorkflows": 35,
      "avgProcessingTime": 3.4,
      "completionRate": 0.969,
      "exceptions": 12,
      "originationWorkflows": 11,
      "creditWorkflows": 12,
      "distributionWorkflows": 7,
      "originationProgress": 72.7,
      "creditProgress": 71.7,
      "distributionProgress": 80.2
    },
    {
      "reportDate": "2023-08-22",
      "activeWorkflows": 42,
      "avgProcessingTime": 3.5,
      "completionRate": 0.957,
      "exceptions": 13,
      "originationWorkflows": 16,
      "creditWorkflows": 10,
      "distributionWorkflows": 6,
      "originationProgress": 77.8,
      "creditProgress": 69.0,
      "distributionProgress": 83.9
    },
    {
      "reportDate": "2023-07-23",
      "activeWorkflows": 31,
      "avgProcessingTime": 4.3,
      "completionRate": 0.955,
      "exceptions": 7,
      "originationWorkflows": 18,
      "creditWorkflows": 16,
      "distributionWorkflows": 10,
      "originationProgress": 73.0,
      "creditProgress": 63.0,
      "distributionProgress": 84.3
    },
    {
      "reportDate": "2023-06-23",
      "activeWorkflows": 27,
      "avgProcessingTime": 2.8,
      "completionRate": 0.974,
      "exceptions": 15,
      "originationWorkflows": 18,
      "creditWorkflows": 18,
      "distributionWorkflows": 6,
      "originationProgress": 71.4,
      "creditProgress": 65.4,
      "distributionProgress": 88.7
    },
    {
      "reportDate": "2023-05-24",
      "activeWorkflows": 45,
      "avgProcessingTime": 3.5,
      "completionRate": 0.947,
      "exceptions": 6,
      "originationWorkflows": 20,
      "creditWorkflows": 8,
      "distributionWorkflows": 8,
      "originationProgress": 67.1,
      "creditProgress": 55.5,
      "distributionProgress": 93.8
    },
    {
      "reportDate": "2023-04-24",
      "activeWorkflows": 36,
      "avgProcessingTime": 4.3,
      "completionRate": 0.941,
      "exceptions": 11,
      "originationWorkflows": 13,
      "creditWorkflows": 9,
      "distributionWorkflows": 5,
      "originationProgress": 73.1,
      "creditProgress": 73.2,
      "distributionProgress": 93.0
    },
    {
      "reportDate": "2023-03-25",
      "activeWorkflows": 32,
      "avgProcessingTime": 4.2,
      "completionRate": 0.952,
      "exceptions": 5,
      "originationWorkflows": 13,
      "creditWorkflows": 13,
      "distributionWorkflows": 12,
      "originationProgress": 83.9,
      "creditProgress": 62.8,
      "distributionProgress": 90.6
    },
    {
      "reportDate": "2023-02-23",
      "activeWorkflows": 31,
      "avgProcessingTime": 3.2,
      "completionRate": 0.94,
      "exceptions": 12,
      "originationWorkflows": 14,
      "creditWorkflows": 14,
      "distributionWorkflows": 10,
      "originationProgress": 73.1,
      "creditProgress": 63.8,
      "distributionProgress": 84.1
    },
    {
      "reportDate": "2023-01-24",
      "activeWorkflows": 39,
      "avgProcessingTime": 3.8,
      "completionRate": 0.978,
      "exceptions": 8,
      "originationWorkflows": 17,
      "creditWorkflows": 13,
      "distributionWorkflows": 5,
      "originationProgress": 78.5,
      "creditProgress": 67.6,
      "distributionProgress": 81.2
    },
    {
      "reportDate": "2022-12-25",
      "activeWorkflows": 30,
      "avgProcessingTime": 4.1,
      "completionRate": 0.96,
      "exceptions": 7,
      "originationWorkflows": 16,
      "creditWorkflows": 18,
      "distributionWorkflows": 7,
      "originationProgress": 70.9,
      "creditProgress": 68.6,
      "distributionProgress": 92.7
    },
    {
      "reportDate": "2022-11-25",
      "activeWorkflows": 40,
      "avgProcessingTime": 3.3,
      "completionRate": 0.944,
      "exceptions": 15,
      "originationWorkflows": 12,
      "creditWorkflows": 14,
      "distributionWorkflows": 7,
      "originationProgress": 80.8,
      "creditProgress": 72.7,
      "distributionProgress": 89.5
    },
    {
      "reportDate": "2022-10-26",
      "activeWorkflows": 41,
      "avgProcessingTime": 3.4,
      "completionRate": 0.978,
      "exceptions": 5,
      "originationWorkflows": 13,
      "creditWorkflows": 11,
      "distributionWorkflows": 7,
      "originationProgress": 84.7,
      "creditProgress": 68.6,
      "distributionProgress": 91.6
    },
    {
      "reportDate": "2022-09-26",
      "activeWorkflows": 40,
      "avgProcessingTime": 3.0,
      "completionRate": 0.944,
      "exceptions": 8,
      "originationWorkflows": 15,
      "creditWorkflows": 18,
      "distributionWorkflows": 9,
      "originationProgress": 76.8,
      "creditProgress": 57.8,
      "distributionProgress": 80.4
    },
    {
      "reportDate": "2022-08-27",
      "activeWorkflows": 43,
      "avgProcessingTime": 3.2,
      "completionRate": 0.95,
      "exceptions": 15,
      "originationWorkflows": 18,
      "creditWorkflows": 10,
      "distributionWorkflows": 10,
      "originationProgress": 74.8,
      "creditProgress": 59.3,
      "distributionProgress": 81.4
    },
    {
      "reportDate": "2022-07-28",
      "activeWorkflows": 31,
      "avgProcessingTime": 3.7,
      "completionRate": 0.947,
      "exceptions": 6,
      "originationWorkflows": 11,
      "creditWorkflows": 8,
      "distributionWorkflows": 5,
      "originationProgress": 68.6,
      "creditProgress": 58.6,
      "distributionProgress": 81.3
    },
    {
      "reportDate": "2022-06-28",
      "activeWorkflows": 38,
      "avgProcessingTime": 3.3,
      "completionRate": 0.966,
      "exceptions": 7,
      "originationWorkflows": 18,
      "creditWorkflows": 10,
      "distributionWorkflows": 7,
      "originationProgress": 84.6,
      "creditProgress": 64.2,
      "distributionProgress": 89.3
    },
    {
      "reportDate": "2022-05-29",
      "activeWorkflows": 25,
      "avgProcessingTime": 2.8,
      "completionRate": 0.944,
      "exceptions": 11,
      "originationWorkflows": 11,
      "creditWorkflows": 10,
      "distributionWorkflows": 8,
      "originationProgress": 68.2,
      "creditProgress": 73.0,
      "distributionProgress": 80.7
    },
    {
      "reportDate": "2022-04-29",
      "activeWorkflows": 32,
      "avgProcessingTime": 4.2,
      "completionRate": 0.949,
      "exceptions": 5,
      "originationWorkflows": 17,
      "creditWorkflows": 8,
      "distributionWorkflows": 8,
      "originationProgress": 66.9,
      "creditProgress": 73.7,
      "distributionProgress": 87.8
    },
    {
      "reportDate": "2022-03-30",
      "activeWorkflows": 35,
      "avgProcessingTime": 4.1,
      "completionRate": 0.924,
      "exceptions": 15,
      "originationWorkflows": 20,
      "creditWorkflows": 11,
      "distributionWorkflows": 12,
      "originationProgress": 71.4,
      "creditProgress": 73.1,
      "distributionProgress": 81.5
    },
    {
      "reportDate": "2022-02-28",
      "activeWorkflows": 34,
      "avgProcessingTime": 3.4,
      "completionRate": 0.93,
      "exceptions": 7,
      "originationWorkflows": 13,
      "creditWorkflows": 13,
      "distributionWorkflows": 6,
      "originationProgress": 70.6,
      "creditProgress": 62.7,
      "distributionProgress": 83.7
    },
    {
      "reportDate": "2022-01-29",
      "activeWorkflows": 37,
      "avgProcessingTime": 4.4,
      "completionRate": 0.942,
      "exceptions": 11,
      "originationWorkflows": 19,
      "creditWorkflows": 10,
      "distributionWorkflows": 10,
      "originationProgress": 84.4,
      "creditProgress": 64.3,
      "distributionProgress": 83.1
    },
    {
      "reportDate": "2021-12-30",
      "activeWorkflows": 29,
      "avgProcessingTime": 3.5,
      "completionRate": 0.973,
      "exceptions": 5,
      "originationWorkflows": 11,
      "creditWorkflows": 16,
      "distributionWorkflows": 11,
      "originationProgress": 73.7,
      "creditProgress": 64.4,
      "distributionProgress": 92.4
    },
    {
      "reportDate": "2021-11-30",
      "activeWorkflows": 26,
      "avgProcessingTime": 3.3,
      "completionRate": 0.978,
      "exceptions": 13,
      "originationWorkflows": 20,
      "creditWorkflows": 16,
      "distributionWorkflows": 10,
      "originationProgress": 70.5,
      "creditProgress": 64.3,
      "distributionProgress": 93.2
    },
    {
      "reportDate": "2021-10-31",
      "activeWorkflows": 41,
      "avgProcessingTime": 3.3,
      "completionRate": 0.926,
      "exceptions": 6,
      "originationWorkflows": 14,
      "creditWorkflows": 13,
      "distributionWorkflows": 8,
      "originationProgress": 76.8,
      "creditProgress": 56.0,
      "distributionProgress": 89.3
    },
    {
      "reportDate": "2021-10-01",
      "activeWorkflows": 28,
      "avgProcessingTime": 3.1,
      "completionRate": 0.961,
      "exceptions": 14,
      "originationWorkflows": 11,
      "creditWorkflows": 18,
      "distributionWorkflows": 7,
      "originationProgress": 69.9,
      "creditProgress": 57.9,
      "distributionProgress": 91.4
    },
    {
      "reportDate": "2021-09-01",
      "activeWorkflows": 31,
      "avgProcessingTime": 3.9,
      "completionRate": 0.979,
      "exceptions": 6,
      "originationWorkflows": 20,
      "creditWorkflows": 11,
      "distributionWorkflows": 9,
      "originationProgress": 83.7,
      "creditProgress": 74.1,
      "distributionProgress": 92.3
    }
  ]
}